XMZAPI/APM.py
XMZAPI/ERNIEBot1.py
XMZAPI/KMS.py
XMZAPI/KVS.py
XMZAPI/__init__.py
XMZAPI/aistudio.py
XMZAPI/alidns.py
XMZAPI/chageng.py
XMZAPI/headers.py
XMZAPI-1.0.8.dist-info/LICENSE
XMZAPI-1.0.8.dist-info/METADATA
XMZAPI-1.0.8.dist-info/WHEEL
XMZAPI-1.0.8.dist-info/top_level.txt
XMZAPI-1.0.8.dist-info/RECORD
